cli_logger/__init__.py
cli_logger/cli_logger.py
cli_logger-1.0.1.dist-info/LICENSE
cli_logger-1.0.1.dist-info/METADATA
cli_logger-1.0.1.dist-info/WHEEL
cli_logger-1.0.1.dist-info/top_level.txt
cli_logger-1.0.1.dist-info/RECORD
