Metadata-Version: 2.1
Name: cli-logger
Version: 1.0.1
Summary: A module to pretty-print outputs for command-line programs.
Home-page: https://github.com/TomMeHo/cli_logger
Author: Thomas Meder
Author-email: tom@tommho.net
License: BSD
Platform: UNKNOWN
Classifier: Programming Language :: Python :: 3
Classifier: License :: OSI Approved :: MIT License
Classifier: Operating System :: OS Independent
Classifier: Topic :: System :: Logging
Requires-Python: >=3.6
Requires-Dist: click (>=7.1.2)
Requires-Dist: colorama (>=0.4.4)
Requires-Dist: datetime (>=4.3)
